src/control_unit.sv
module control_unit #(
  parameter INSTR_LEN = 32
)(
  input logic [INSTR_LEN-1:0] instr,
  input logic EQ,
  output logic RegWrite,
  output logic [2:0] ALUctrl,
  output logic ALUsrc,
  output logic [1:0] Immsrc,
  output logic PCsrc
);

// note: unify indentation scheme
// note: add begin and end for multiline statements
always_comb begin
  case(instr[6:0])
    7'b0010011: begin // addi
      case(instr[14:12])
        3'b000: begin
          ALUctrl = 3'b000;
          ALUsrc = 1;
        end
        default: begin
          ALUctrl = 3'b000;
          ALUsrc = 0;
        end
      endcase
      RegWrite = 1;
      PCsrc = 0;
      Immsrc = 2'b00;
    end

    7'b1100011: begin // bne & beq
      case(instr[14:12])
        3'b000: 
          PCsrc = EQ;
        3'b001: 
          PCsrc = ~EQ;
        default: 
          PCsrc = 0;
      endcase
      RegWrite = 0;
      Immsrc = 2'b01;
      ALUctrl = 3'b001; 
      ALUsrc = 0;
    end

    default: begin
      RegWrite = 0;
      ALUctrl = 2'b00;
      ALUsrc = 0;
      Immsrc = 0;
      PCsrc = 0;
    end
  endcase
end

// note: remove unused code

endmodule

src/instr_mem.sv
module instr_mem #(
  // note: use correct naming convention for parameters
  parameter INSTR_LEN = 32,
  parameter ADDR_LEN = 8
)(
  // note: use correct name for component externals
  input logic [ADDR_LEN-1:0] A,
  output logic [INSTR_LEN-1:0] RD
);

logic [INSTR_LEN-1:0] instr_data [2**ADDR_LEN-1:0];

initial begin
  $display("[DUT] Load instr_mem from instr.mem file.");
  $readmemh("instr.mem", instr_data);
end

// note: right shift A by 2 digits for byte addressing
assign RD = instr_data[{2'b0, A[ADDR_LEN-1:2]}];

endmodule

src/control_unit_top.sv
module control_unit_top #(
    parameter INSTR_LEN = 32,
    parameter ADDR_LEN = 8
) (
    input logic [ADDR_LEN-1:0] A,
    input logic EQ,
    output logic RegWrite,
    output logic [2:0] ALUctrl,
    output logic ALUsrc,
    output logic [1:0] Immsrc,
    output logic PCsrc
);

logic [INSTR_LEN-1:0] RD;

instr_mem instr_mem(
.A(A),
.RD(RD)
);

control_unit control_unit(
.instr(RD),
.EQ(EQ),
.RegWrite(RegWrite),
.ALUctrl(ALUctrl),
.ALUsrc(ALUsrc),
.Immsrc(Immsrc),
.PCsrc(PCsrc)
);   
endmodule

src/Vcontrol_unit_top.vcd
$version Generated by VerilatedVcd $end
$date Fri Nov 25 19:04:51 2022 $end
$timescale 1ps $end

 $scope module TOP $end
  $var wire  8 # A [7:0] $end
  $var wire  3 & ALUctrl [2:0] $end
  $var wire  1 ' ALUsrc $end
  $var wire  1 $ EQ $end
  $var wire  2 ( Immsrc [1:0] $end
  $var wire  1 ) PCsrc $end
  $var wire  1 % RegWrite $end
  $scope module control_unit_top $end
   $var wire  8 # A [7:0] $end
   $var wire 32 , ADDR_LEN [31:0] $end
   $var wire  3 & ALUctrl [2:0] $end
   $var wire  1 ' ALUsrc $end
   $var wire  1 $ EQ $end
   $var wire 32 + INSTR_LEN [31:0] $end
   $var wire  2 ( Immsrc [1:0] $end
   $var wire  1 ) PCsrc $end
   $var wire 32 * RD [31:0] $end
   $var wire  1 % RegWrite $end
   $scope module control_unit $end
    $var wire  3 & ALUctrl [2:0] $end
    $var wire  1 ' ALUsrc $end
    $var wire  1 $ EQ $end
    $var wire 32 + INSTR_LEN [31:0] $end
    $var wire  2 ( Immsrc [1:0] $end
    $var wire  1 ) PCsrc $end
    $var wire  1 % RegWrite $end
    $var wire 32 * instr [31:0] $end
   $upscope $end
   $scope module instr_mem $end
    $var wire  8 # A [7:0] $end
    $var wire 32 , ADDR_LEN [31:0] $end
    $var wire 32 + INSTR_LEN [31:0] $end
    $var wire 32 * RD [31:0] $end
   $upscope $end
  $upscope $end
 $upscope $end
$enddefinitions $end


#0
b00000000 #
0$
0%
b000 &
0'
b00 (
0)
b00000000000000000000000000000000 *
b00000000000000000000000000100000 +
b00000000000000000000000000001000 ,
#1
1%
1'
b00001111111100000000001100010011 *
#2
#3
#4
#5
#6
#7
#8
#9
#10
b00000100 #
#11
b00000000000000000000010100010011 *
#12
#13
#14
#15
#16
#17
#18
b00001000 #
#19
b00000000000000000000010110010011 *
#20
#21
#22
#23
#24
#25
#26
b00001100 #
#27
b00000000000001011000010100010011 *
#28
#29
#30
#31
#32
#33
#34
b00010000 #
#35
b00000000000101011000010110010011 *
#36
#37
#38
#39
#40
#41
#42
b00010100 #
#43
0%
b001 &
0'
b01 (
1)
b11111110011001011001110011100011 *
#44
#45
#46
#47
#48
#49
#50
b00011000 #
#51
b000 &
b00 (
0)
b00000000000000000000000000000000 *
#52
#53
#54
#55
#56
#57
#58
b00011100 #
#59
#60
#61
#62
#63
#64
#65
#66
b00100000 #
#67
#68
#69
#70
#71
#72
#73
#74
b00100100 #
#75
#76
#77
#78
#79
#80
#81
#82
b00101000 #
#83
#84
#85
#86
#87
#88
#89
#90
b00101100 #
#91
#92
#93
#94
#95
#96
#97
#98
b00110000 #
#99
#100
#101
#102
#103
#104
#105
#106
b00110100 #
#107
#108
#109
#110
#111
#112
#113
#114
b00111000 #
#115
#116
#117
#118
#119
#120
#121
#122
b00111100 #
#123
#124
#125
#126
#127
#128
#129
#130
b01000000 #
#131
#132
#133
#134
#135
#136
#137
#138
b01000100 #
#139
#140
#141
#142
#143
#144
#145
#146
b01001000 #
#147
#148
#149
#150
#151
#152
#153
#154
b01001100 #
#155
#156
#157
#158
#159
#160
#161
#162
b01010000 #
#163
#164
#165
#166
#167
#168
#169
#170
b01010100 #
#171
#172
#173
#174
#175
#176
#177
#178
b01011000 #
#179
#180
#181
#182
#183
#184
#185
#186
b01011100 #
#187
#188
#189
#190
#191
#192
#193
#194
b01100000 #
#195
#196
#197
#198
#199
#200
#201
#202
b01100100 #
#203
#204
#205
#206
#207
#208
#209
#210
b01101000 #
#211
#212
#213
#214
#215
#216
#217
#218
b01101100 #
#219
#220
#221
#222
#223
#224
#225
#226
b01110000 #
#227
#228
#229
#230
#231
#232
#233
#234
b01110100 #
#235
#236
#237
#238
#239
#240
#241
#242
b01111000 #
#243
#244
#245
#246
#247
#248
#249
#250
b01111100 #
#251
#252
#253
#254
#255
#256
#257
#258
b10000000 #
#259
#260
#261
#262
#263
#264
#265
#266
b10000100 #
#267
#268
#269
#270
#271
#272
#273
#274
b10001000 #
#275
#276
#277
#278
#279
#280
#281
#282
b10001100 #
#283
#284
#285
#286
#287
#288
#289
#290
b10010000 #
#291
#292
#293
#294
#295
#296
#297
#298
b10010100 #
#299
#300
#301
#302
#303
#304
#305
#306
b10011000 #
#307
#308
#309
#310
#311
#312
#313
#314
b10011100 #
#315
#316
#317
#318
#319
#320
#321
#322
b10100000 #
#323
#324
#325
#326
#327
#328
#329
#330
b10100100 #
#331
#332
#333
#334
#335
#336
#337
#338
b10101000 #
#339
#340
#341
#342
#343
#344
#345
#346
b10101100 #
#347
#348
#349
#350
#351
#352
#353
#354
b10110000 #
#355
#356
#357
#358
#359
#360
#361
#362
b10110100 #
#363
#364
#365
#366
#367
#368
#369
#370
b10111000 #
#371
#372
#373
#374
#375
#376
#377
#378
b10111100 #
#379
#380
#381
#382
#383
#384
#385
#386
b11000000 #
#387
#388
#389
#390
#391
#392
#393
#394
b11000100 #
#395
#396
#397
#398
#399
#400
#401
#402
b11001000 #
#403
#404
#405
#406
#407
#408
#409
#410
b11001100 #
#411
#412
#413
#414
#415
#416
#417
#418
b11010000 #
#419
#420
#421
#422
#423
#424
#425
#426
b11010100 #
#427
#428
#429
#430
#431
#432
#433
#434
b11011000 #
#435
#436
#437
#438
#439
#440
#441
#442
b11011100 #
#443
#444
#445
#446
#447
#448
#449
#450
b11100000 #
#451
#452
#453
#454
#455
#456
#457
#458
b11100100 #
#459
#460
#461
#462
#463
#464
#465
#466
b11101000 #
#467
#468
#469
#470
#471
#472
#473
#474
b11101100 #
#475
#476
#477
#478
#479
#480
#481
#482
b11110000 #
#483
#484
#485
#486
#487
#488
#489
#490
b11110100 #
#491
#492
#493
#494
#495
#496
#497
#498
b11111000 #
#499
#500
#501
#502
#503
#504
#505
#506
b11111100 #
#507
#508
#509
#510
#511
#512
#513
#514
b00000000 #
#515
1%
1'
b00001111111100000000001100010011 *
#516
#517
#518
#519
#520
#521
#522
b00000100 #
#523
b00000000000000000000010100010011 *
#524
#525
#526
#527
#528
#529
#530
b00001000 #
#531
b00000000000000000000010110010011 *
#532
#533
#534
#535
#536
#537
#538
b00001100 #
#539
b00000000000001011000010100010011 *
#540
#541
#542
#543
#544
#545
#546
b00010000 #
#547
b00000000000101011000010110010011 *
#548
#549
#550
#551
#552
#553
#554
b00010100 #
#555
0%
b001 &
0'
b01 (
1)
b11111110011001011001110011100011 *
#556
#557
#558
#559
#560
#561
#562
b00011000 #
#563
b000 &
b00 (
0)
b00000000000000000000000000000000 *
#564
#565
#566
#567
#568
#569
#570
b00011100 #
#571
#572
#573
#574
#575
#576
#577
#578
b00100000 #
#579
#580
#581
#582
#583
#584
#585
#586
b00100100 #
#587
#588
#589
#590
#591
#592
#593
#594
b00101000 #
